sqlalchemy_pydantic_type/__init__.py
sqlalchemy_pydantic_type/_version.py
sqlalchemy_pydantic_type/core.py
sqlalchemy_pydantic_type/py.typed
sqlalchemy_pydantic_type/alembic/__init__.py
sqlalchemy_pydantic_type/alembic/render_item.py
sqlalchemy_pydantic_type-0.0.1.dist-info/METADATA
sqlalchemy_pydantic_type-0.0.1.dist-info/WHEEL
sqlalchemy_pydantic_type-0.0.1.dist-info/licenses/AUTHORS.md
sqlalchemy_pydantic_type-0.0.1.dist-info/licenses/LICENSE.txt
sqlalchemy_pydantic_type-0.0.1.dist-info/RECORD
