Metadata-Version: 2.4
Name: sqlalchemy-pydantic-type
Version: 0.0.1
Summary: SQLAlchemy custom type to automatically serialize/deserialize pydantic models
Project-URL: Documentation, https://github.com/bartosz121/sqlalchemy-pydantic-type
Project-URL: Source, https://github.com/bartosz121/sqlalchemy-pydantic-type
Project-URL: Tracker, https://github.com/bartosz121/sqlalchemy-pydantic-type/issues
Author-email: Bartosz Magiera <admin@bartoszmagiera.dev>
License: MIT
License-File: AUTHORS.md
License-File: LICENSE.txt
Keywords: alembic,pydantic,sqlalchemy,sqlalchemy-pydantic-type
Classifier: Development Status :: 2 - Pre-Alpha
Classifier: Programming Language :: Python
Classifier: Programming Language :: Python :: 3.10
Classifier: Programming Language :: Python :: 3.11
Classifier: Programming Language :: Python :: 3.12
Classifier: Programming Language :: Python :: 3.13
Classifier: Programming Language :: Python :: Implementation :: CPython
Requires-Python: >=3.10
Requires-Dist: pydantic>=2
Requires-Dist: sqlalchemy>=2
Provides-Extra: alembic
Requires-Dist: alembic>=1; extra == 'alembic'
